collective.cloudfront-2.0-py3.11-nspkg.pth
collective/cloudfront/__init__.py
collective/cloudfront/configure.zcml
collective/cloudfront/events.py
collective/cloudfront/interfaces.py
collective/cloudfront/setuphandlers.py
collective/cloudfront/testing.py
collective/cloudfront/upgrades.py
collective/cloudfront/browser/__init__.py
collective/cloudfront/browser/configure.zcml
collective/cloudfront/browser/controlpanel.py
collective/cloudfront/browser/interfaces.py
collective/cloudfront/browser/settings.pt
collective/cloudfront/browser/static/.gitkeep
collective/cloudfront/locales/collective.cloudfront.pot
collective/cloudfront/locales/update.sh
collective/cloudfront/profiles/default/browserlayer.xml
collective/cloudfront/profiles/default/controlpanel.xml
collective/cloudfront/profiles/default/metadata.xml
collective/cloudfront/profiles/default/registry.xml
collective/cloudfront/profiles/initial/collective.cloudfront-initial.txt
collective/cloudfront/profiles/initial/propertiestool.xml
collective/cloudfront/profiles/initial/rolemap.xml
collective/cloudfront/profiles/uninstall/browserlayer.xml
collective/cloudfront/profiles/uninstall/controlpanel.xml
collective/cloudfront/tests/__init__.py
collective/cloudfront/tests/test_robot.py
collective/cloudfront/tests/test_setup.py
collective/cloudfront/tests/robot/test_example.robot
collective.cloudfront-2.0.dist-info/METADATA
collective.cloudfront-2.0.dist-info/WHEEL
collective.cloudfront-2.0.dist-info/entry_points.txt
collective.cloudfront-2.0.dist-info/namespace_packages.txt
collective.cloudfront-2.0.dist-info/top_level.txt
collective.cloudfront-2.0.dist-info/RECORD
