Metadata-Version: 2.1
Name: collective.cloudfront
Version: 2.0
Summary: AWS CloudFront support for plone.app.caching
Home-page: https://github.com/collective/collective.cloudfront
Author: Six Feet Up
Author-email: info@sixfeetup.com
License: GPL version 2
Project-URL: PyPI, https://pypi.python.org/pypi/collective.cloudfront
Project-URL: Source, https://github.com/collective/collective.cloudfront
Project-URL: Tracker, https://github.com/collective/collective.cloudfront/issues
Keywords: Python Plone
Classifier: Environment :: Web Environment
Classifier: Framework :: Plone
Classifier: Framework :: Plone :: Addon
Classifier: Framework :: Plone :: 6.0
Classifier: Programming Language :: Python
Classifier: Programming Language :: Python :: 3.8
Classifier: Programming Language :: Python :: 3.9
Classifier: Programming Language :: Python :: 3.10
Classifier: Programming Language :: Python :: 3.11
Classifier: Operating System :: OS Independent
Classifier: License :: OSI Approved :: GNU General Public License v2 (GPLv2)
Requires-Dist: boto3
Requires-Dist: plone.app.caching
Requires-Dist: Products.GenericSetup >=1.8.2
Requires-Dist: setuptools
Provides-Extra: test
Requires-Dist: plone.app.testing ; extra == 'test'
Requires-Dist: plone.testing >=5.0.0 ; extra == 'test'
Requires-Dist: plone.app.contenttypes ; extra == 'test'
Requires-Dist: plone.app.robotframework[debug] ; extra == 'test'
